pyramid_ptpython.py
pyramid_ptpython/__init__.py
pyramid_ptpython-1.2.dist-info/DESCRIPTION.rst
pyramid_ptpython-1.2.dist-info/METADATA
pyramid_ptpython-1.2.dist-info/RECORD
pyramid_ptpython-1.2.dist-info/WHEEL
pyramid_ptpython-1.2.dist-info/entry_points.txt
pyramid_ptpython-1.2.dist-info/metadata.json
pyramid_ptpython-1.2.dist-info/top_level.txt
pyramid_ptpython-1.2.dist-info/zip-safe
