Metadata-Version: 2.0
Name: pyramid-ptpython
Version: 1.2
Summary: A ptpython and ptipython plugin for pyramid pshell
Home-page: https://github.com/dakra/pyramid_ptpython
Author: Daniel Kraus
Author-email: dakra-python@tr0ll.net
License: ISC
Keywords: pyramid pshell ptpython
Platform: UNKNOWN
Classifier: Development Status :: 4 - Beta
Classifier: Intended Audience :: Developers
Classifier: Framework :: Pyramid
Classifier: License :: OSI Approved :: ISC License (ISCL)
Classifier: Programming Language :: Python :: 2
Classifier: Programming Language :: Python :: 3
Classifier: Topic :: Software Development :: Libraries :: Python Modules
Requires-Dist: ptpython
Requires-Dist: pyramid (>1.6a2)
Provides-Extra: ipython
Requires-Dist: ipython; extra == 'ipython'
